{
  "utrecht": {
    "form-field": {
      "margin-block-start": { "value": "{haarlem.space.100}" },
      "margin-block-end": { "value": "{haarlem.space.100}" },
      "invalid": {
        "border-inline-start-color": {},
        "border-inline-start-width": { "value": "3px" },
        "padding-inline-start": { "value": "{haarlem.space.75}" }
      },
      "label": {
        "margin-block-end": { "value": "{haarlem.space.75}" }
      },
      "description": {
        "margin-block-start": { "value": "{haarlem.space.75}" },
        "margin-block-end": { "value": "{haarlem.space.75}" }
      }
    }
  }
}
