{
  "utrecht": {
    "form-input": {
      "block-size": { "value": "44px" },
      "color": { "value": "{bodegraven.color.grey.10.value}" },
      "border-color": { "value": "{bodegraven.color.blue.40.value}" },
      "border-width": { "value": "1px" },
      "font-family": { "value": "{bodegraven.typography.sans-serif.font-family.value}" },
      "font-size": { "value": "16px" },
      "line-height": {},
      "padding-inline-start": { "value": "15px" },
      "padding-inline-end": { "value": "15px" },
      "padding-block-start": { "value": "10px" },
      "padding-block-end": { "value": "10px" },
      "max-inline-size": { "value": "460px" },
      "placeholder": {
        "color": { "value": "{bodegraven.color.grey.30.value}" }
      },
      "focus": {
        "border-color": { "value": "{bodegraven.color.blue.30.value}" }
      },
      "hover": {
        "border-color": { "value": "{bodegraven.color.blue.30.value}" }
      }
    }
  }
}
