{
  "conduction": {
    "card-wrapper": {
      "background-color": { "value": "{xxllnc.color.black.21}" },
      "border-color": {},
      "border-style": {},
      "border-width": { "value": "unset" },
      "border-bottom-color": {},
      "border-bottom-style": {},
      "border-bottom-width": {},
      "border-radius": { "value": "{xxllnc.size.md}" },
      "color": { "value": "{xxllnc.color.white.95}" },
      "hover": {
        "background-color": {},
        "border-bottom-color": {},
        "border-bottom-style": {},
        "border-bottom-width": {}
      },
      "padding-inline-end": { "value": "{xxllnc.size.md}" },
      "padding-inline-start": { "value": "{xxllnc.size.md}" },
      "padding-block-end": { "value": "{xxllnc.size.md}" },
      "padding-block-start": { "value": "{xxllnc.size.md}" }
    }
  }
}
